esm/__init__.py
esm/axial_attention.py
esm/constants.py
esm/data.py
esm/modules.py
esm/multihead_attention.py
esm/pretrained.py
esm/rotary_embedding.py
esm/version.py
esm/esmfold/v1/__init__.py
esm/esmfold/v1/categorical_mixture.py
esm/esmfold/v1/esmfold.py
esm/esmfold/v1/misc.py
esm/esmfold/v1/pretrained.py
esm/esmfold/v1/tri_self_attn_block.py
esm/esmfold/v1/trunk.py
esm/inverse_folding/__init__.py
esm/inverse_folding/features.py
esm/inverse_folding/gvp_encoder.py
esm/inverse_folding/gvp_modules.py
esm/inverse_folding/gvp_transformer.py
esm/inverse_folding/gvp_transformer_encoder.py
esm/inverse_folding/gvp_utils.py
esm/inverse_folding/multichain_util.py
esm/inverse_folding/transformer_decoder.py
esm/inverse_folding/transformer_layer.py
esm/inverse_folding/util.py
esm/model/esm1.py
esm/model/esm2.py
esm/model/msa_transformer.py
fair_esm-2.0.0.data/data/source_docs/esm/CODE_OF_CONDUCT.rst
fair_esm-2.0.0.data/data/source_docs/esm/LICENSE
fair_esm-2.0.0.data/data/source_docs/esm/README.md
fair_esm-2.0.0.dist-info/LICENSE
fair_esm-2.0.0.dist-info/METADATA
fair_esm-2.0.0.dist-info/WHEEL
fair_esm-2.0.0.dist-info/top_level.txt
fair_esm-2.0.0.dist-info/zip-safe
fair_esm-2.0.0.dist-info/RECORD
