Metadata-Version: 2.1
Name: fair-esm
Version: 2.0.0
Summary: Evolutionary Scale Modeling (esm): Pretrained language models for proteins. From Facebook AI Research.
Home-page: https://github.com/facebookresearch/esm
Author: Facebook AI Research
License: MIT
Provides-Extra: esmfold
License-File: LICENSE
